HISTORY.txt
README.txt
ez_setup.py
setup.cfg
setup.py
src/ClueMapper.egg-info/PKG-INFO
src/ClueMapper.egg-info/SOURCES.txt
src/ClueMapper.egg-info/dependency_links.txt
src/ClueMapper.egg-info/entry_points.txt
src/ClueMapper.egg-info/namespace_packages.txt
src/ClueMapper.egg-info/requires.txt
src/ClueMapper.egg-info/top_level.txt
src/ClueMapper.egg-info/zip-safe
src/clue/__init__.py
src/clue/app/__init__.py
src/clue/app/admin.py
src/clue/app/cluemapper.txt
src/clue/app/config.py
src/clue/app/controller.py
src/clue/app/environinit.py
src/clue/app/patches.py
src/clue/app/pdbcheck.py
src/clue/app/project.py
src/clue/app/redirect.py
src/clue/app/server.py
src/clue/app/tests.py
src/clue/app/utils.py
src/clue/app/skel/trac.ini.template
src/clue/app/templates/error-404.html
src/clue/app/templates/main.html
src/clue/app/templates/project-created.html
src/clue/app/tracplugins/__init__.py
src/clue/app/tracplugins/sourcecontrol.py
src/clue/app/tracplugins/theme.py
src/clue/app/tracplugins/user.py
src/clue/app/tracplugins/htdocs/cluemaperthemer.css
src/clue/app/tracplugins/templates/admin-sourcecontrol.html
src/clue/app/tracplugins/templates/admin-themeconfig.html