Metadata-Version: 1.0
Name: ClueMapper
Version: 0.7
Summary: A web-based application for managing software projects.
Home-page: http://projects.serverzen.com/pm/p/cluemapper
Author: Rocky Burt
Author-email: rocky@serverzen.com
License: BSD
Platform: UNKNOWN
Classifier: Programming Language :: Python
Classifier: Topic :: Software Development :: Libraries :: Python Modules
